.gitignore
.travis.yml
LICENSE.txt
MANIFEST.in
README.md
README.rst
requirements.txt
setup.cfg
setup.py
Orange3_Conformal.egg-info/PKG-INFO
Orange3_Conformal.egg-info/SOURCES.txt
Orange3_Conformal.egg-info/dependency_links.txt
Orange3_Conformal.egg-info/entry_points.txt
Orange3_Conformal.egg-info/namespace_packages.txt
Orange3_Conformal.egg-info/not-zip-safe
Orange3_Conformal.egg-info/requires.txt
Orange3_Conformal.egg-info/top_level.txt
doc/Makefile
doc/Orange-ConformalPrediction.pdf
doc/conf.py
doc/conformal.base.rst
doc/conformal.classification.rst
doc/conformal.evaluation.rst
doc/conformal.nonconformity.rst
doc/conformal.regression.rst
doc/conformal.rst
doc/conformal_ext.py
doc/index.rst
doc/make.bat
doc/tutorial.classification.rst
doc/tutorial.evaluation.rst
doc/tutorial.intro.rst
doc/tutorial.regression.rst
doc/tutorial.rst
orangecontrib/__init__.py
orangecontrib/conformal/__init__.py
orangecontrib/conformal/base.py
orangecontrib/conformal/classification.py
orangecontrib/conformal/evaluation.py
orangecontrib/conformal/nonconformity.py
orangecontrib/conformal/regression.py
orangecontrib/conformal/datasets/usps.tab
orangecontrib/conformal/tests/__init__.py
orangecontrib/conformal/tests/test_evaluation.py
orangecontrib/conformal/tests/test_example.py
orangecontrib/conformal/tests/test_methods.py
orangecontrib/conformal/tests/test_nonconformity.py