Metadata-Version: 1.0
Name: Orange3-Conformal
Version: 1.1.3
Summary: Orange3 Conformal Prediction library
Home-page: https://github.com/biolab/orange3-conformal
Author: Bioinformatics Laboratory, FRI UL
Author-email: info@biolab.si
License: GPLv3
Platform: UNKNOWN
